{"ID":1,"Name":"Person_1","Age":18,"Country":"Australia"}
{"ID":2,"Name":"Person_2","Age":21,"Country":"UK"}
{"ID":3,"Name":"Person_3","Age":21,"Country":"UK"}
{"ID":4,"Name":"Person_4","Age":57,"Country":"France"}
{"ID":5,"Name":"Person_5","Age":27,"Country":"USA"}
{"ID":6,"Name":"Person_6","Age":37,"Country":"France"}
{"ID":7,"Name":"Person_7","Age":39,"Country":"Canada"}
{"ID":8,"Name":"Person_8","Age":54,"Country":"USA"}
{"ID":9,"Name":"Person_9","Age":41,"Country":"UK"}
{"ID":10,"Name":"Person_10","Age":24,"Country":"UK"}
{"ID":11,"Name":"Person_11","Age":42,"Country":"Australia"}
{"ID":12,"Name":"Person_12","Age":42,"Country":"UK"}
{"ID":13,"Name":"Person_13","Age":30,"Country":"Australia"}
{"ID":14,"Name":"Person_14","Age":19,"Country":"UK"}
{"ID":15,"Name":"Person_15","Age":56,"Country":"Canada"}
{"ID":16,"Name":"Person_16","Age":57,"Country":"UK"}
{"ID":17,"Name":"Person_17","Age":41,"Country":"Australia"}
{"ID":18,"Name":"Person_18","Age":42,"Country":"Australia"}
{"ID":19,"Name":"Person_19","Age":35,"Country":"Australia"}
{"ID":20,"Name":"Person_20","Age":55,"Country":"UK"}
{"ID":21,"Name":"Person_21","Age":43,"Country":"Australia"}
{"ID":22,"Name":"Person_22","Age":31,"Country":"Germany"}
{"ID":23,"Name":"Person_23","Age":26,"Country":"Canada"}
{"ID":24,"Name":"Person_24","Age":27,"Country":"UK"}
{"ID":25,"Name":"Person_25","Age":38,"Country":"Australia"}
{"ID":26,"Name":"Person_26","Age":34,"Country":"Canada"}
{"ID":27,"Name":"Person_27","Age":23,"Country":"UK"}
{"ID":28,"Name":"Person_28","Age":33,"Country":"Canada"}
{"ID":29,"Name":"Person_29","Age":18,"Country":"Germany"}
{"ID":30,"Name":"Person_30","Age":36,"Country":"UK"}
{"ID":31,"Name":"Person_31","Age":53,"Country":"Australia"}
{"ID":32,"Name":"Person_32","Age":42,"Country":"USA"}
{"ID":33,"Name":"Person_33","Age":47,"Country":"Australia"}
{"ID":34,"Name":"Person_34","Age":37,"Country":"UK"}
{"ID":35,"Name":"Person_35","Age":37,"Country":"Australia"}
{"ID":36,"Name":"Person_36","Age":32,"Country":"USA"}
{"ID":37,"Name":"Person_37","Age":57,"Country":"USA"}
{"ID":38,"Name":"Person_38","Age":50,"Country":"USA"}
{"ID":39,"Name":"Person_39","Age":19,"Country":"Australia"}
{"ID":40,"Name":"Person_40","Age":27,"Country":"UK"}
{"ID":41,"Name":"Person_41","Age":50,"Country":"Australia"}
{"ID":42,"Name":"Person_42","Age":49,"Country":"USA"}
{"ID":43,"Name":"Person_43","Age":28,"Country":"Germany"}
{"ID":44,"Name":"Person_44","Age":41,"Country":"USA"}
{"ID":45,"Name":"Person_45","Age":53,"Country":"France"}
{"ID":46,"Name":"Person_46","Age":29,"Country":"USA"}
{"ID":47,"Name":"Person_47","Age":46,"Country":"France"}
{"ID":48,"Name":"Person_48","Age":52,"Country":"UK"}
{"ID":49,"Name":"Person_49","Age":18,"Country":"Australia"}
{"ID":50,"Name":"Person_50","Age":18,"Country":"UK"}
{"ID":51,"Name":"Person_51","Age":54,"Country":"Australia"}
{"ID":52,"Name":"Person_52","Age":23,"Country":"France"}
{"ID":53,"Name":"Person_53","Age":56,"Country":"USA"}
{"ID":54,"Name":"Person_54","Age":58,"Country":"USA"}
{"ID":55,"Name":"Person_55","Age":35,"Country":"USA"}
{"ID":56,"Name":"Person_56","Age":33,"Country":"Australia"}
{"ID":57,"Name":"Person_57","Age":22,"Country":"USA"}
{"ID":58,"Name":"Person_58","Age":59,"Country":"UK"}
{"ID":59,"Name":"Person_59","Age":49,"Country":"UK"}
{"ID":60,"Name":"Person_60","Age":19,"Country":"USA"}
{"ID":61,"Name":"Person_61","Age":19,"Country":"Germany"}
{"ID":62,"Name":"Person_62","Age":57,"Country":"Australia"}
{"ID":63,"Name":"Person_63","Age":59,"Country":"Germany"}
{"ID":64,"Name":"Person_64","Age":53,"Country":"France"}
{"ID":65,"Name":"Person_65","Age":56,"Country":"USA"}
{"ID":66,"Name":"Person_66","Age":29,"Country":"Germany"}
{"ID":67,"Name":"Person_67","Age":36,"Country":"Australia"}
{"ID":68,"Name":"Person_68","Age":45,"Country":"France"}
{"ID":69,"Name":"Person_69","Age":18,"Country":"Australia"}
{"ID":70,"Name":"Person_70","Age":32,"Country":"Germany"}
{"ID":71,"Name":"Person_71","Age":53,"Country":"France"}
{"ID":72,"Name":"Person_72","Age":30,"Country":"Canada"}
{"ID":73,"Name":"Person_73","Age":38,"Country":"France"}
{"ID":74,"Name":"Person_74","Age":29,"Country":"Australia"}
{"ID":75,"Name":"Person_75","Age":22,"Country":"USA"}
{"ID":76,"Name":"Person_76","Age":24,"Country":"USA"}
{"ID":77,"Name":"Person_77","Age":22,"Country":"USA"}
{"ID":78,"Name":"Person_78","Age":21,"Country":"France"}
{"ID":79,"Name":"Person_79","Age":30,"Country":"France"}
{"ID":80,"Name":"Person_80","Age":54,"Country":"Canada"}
{"ID":81,"Name":"Person_81","Age":58,"Country":"USA"}
{"ID":82,"Name":"Person_82","Age":32,"Country":"Germany"}
{"ID":83,"Name":"Person_83","Age":33,"Country":"Canada"}
{"ID":84,"Name":"Person_84","Age":38,"Country":"France"}
{"ID":85,"Name":"Person_85","Age":53,"Country":"France"}
{"ID":86,"Name":"Person_86","Age":41,"Country":"Australia"}
{"ID":87,"Name":"Person_87","Age":33,"Country":"Canada"}
{"ID":88,"Name":"Person_88","Age":31,"Country":"USA"}
{"ID":89,"Name":"Person_89","Age":39,"Country":"USA"}
{"ID":90,"Name":"Person_90","Age":23,"Country":"Germany"}
{"ID":91,"Name":"Person_91","Age":59,"Country":"Australia"}
{"ID":92,"Name":"Person_92","Age":53,"Country":"Australia"}
{"ID":93,"Name":"Person_93","Age":18,"Country":"Canada"}
{"ID":94,"Name":"Person_94","Age":49,"Country":"France"}
{"ID":95,"Name":"Person_95","Age":23,"Country":"France"}
{"ID":96,"Name":"Person_96","Age":48,"Country":"USA"}
{"ID":97,"Name":"Person_97","Age":18,"Country":"USA"}
{"ID":98,"Name":"Person_98","Age":54,"Country":"Canada"}
{"ID":99,"Name":"Person_99","Age":52,"Country":"UK"}
{"ID":100,"Name":"Person_100","Age":47,"Country":"USA"}
